{
    "name": "沪深300指数",
    "code": "000300",
    "type": "index",
    "market_data": [
        {
            "date": "2024-02-19",
            "pre_close": 3364.93,
            "open": 3393.19,
            "high": 3403.81,
            "low": 3364.14,
            "close": 3403.81,
            "change": 38.88,
            "change_percent": 1.155447513024045,
            "trading_volume": 183319800,
            "trading_value": 267674145147.3,
            "turnover_rate": 0.5921261514852131
        },
        {
            "date": "2024-02-20",
            "pre_close": 3403.81,
            "open": 3395.19,
            "high": 3415.89,
            "low": 3380.1,
            "close": 3410.85,
            "change": 7.04,
            "change_percent": 0.20682705556420597,
            "trading_volume": 140734581,
            "trading_value": 218459281946.0,
            "turnover_rate": 0.4545074774789908
        },
        {
            "date": "2024-02-21",
            "pre_close": 3410.85,
            "open": 3390.36,
            "high": 3500.13,
            "low": 3383.69,
            "close": 3456.87,
            "change": 46.02,
            "change_percent": 1.3492603507366796,
            "trading_volume": 189000000,
            "trading_value": 291824000000.0,
            "turnover_rate": 0.61
        },
        {
            "date": "2024-02-22",
            "pre_close": 3456.87,
            "open": 3450.35,
            "high": 3486.68,
            "low": 3448.41,
            "close": 3486.67,
            "change": 29.8,
            "change_percent": 0.8620515090240594,
            "trading_volume": 141020784,
            "trading_value": 225098128872.7,
            "turnover_rate": 0.45543108783508196
        },
        {
            "date": "2024-02-23",
            "pre_close": 3486.67,
            "open": 3491.34,
            "high": 3507.56,
            "low": 3472.97,
            "close": 3489.74,
            "change": 3.07,
            "change_percent": 0.08804962901565104,
            "trading_volume": 144821273,
            "trading_value": 232926057113.9,
            "turnover_rate": 0.4676965209772345
        },
        {
            "date": "2024-02-26",
            "pre_close": 3489.74,
            "open": 3485.54,
            "high": 3492.61,
            "low": 3445.39,
            "close": 3453.36,
            "change": -36.38,
            "change_percent": -1.0424845403955596,
            "trading_volume": 151248331,
            "trading_value": 238951637715.0,
            "turnover_rate": 0.48844783761583505
        },
        {
            "date": "2024-02-27",
            "pre_close": 3453.36,
            "open": 3440.05,
            "high": 3494.79,
            "low": 3437.44,
            "close": 3494.79,
            "change": 41.43,
            "change_percent": 1.1997011606087984,
            "trading_volume": 139528246,
            "trading_value": 244488721250.8,
            "turnover_rate": 0.4505979544987268
        },
        {
            "date": "2024-02-28",
            "pre_close": 3494.79,
            "open": 3499.83,
            "high": 3521.66,
            "low": 3450.26,
            "close": 3450.26,
            "change": -44.53,
            "change_percent": -1.2741824258396068,
            "trading_volume": 189837548,
            "trading_value": 328300591256.4,
            "turnover_rate": 0.6130687747329231
        },
        {
            "date": "2024-02-29",
            "pre_close": 3450.26,
            "open": 3437.9,
            "high": 3516.08,
            "low": 3437.9,
            "close": 3516.08,
            "change": 65.82,
            "change_percent": 1.9076823195933061,
            "trading_volume": 155944532,
            "trading_value": 281971899288.2,
            "turnover_rate": 0.5036122103169974
        },
        {
            "date": "2024-03-01",
            "pre_close": 3516.08,
            "open": 3515.06,
            "high": 3544.36,
            "low": 3503.46,
            "close": 3537.8,
            "change": 21.72,
            "change_percent": 0.617733384905918,
            "trading_volume": 162709570,
            "trading_value": 288575619224.5,
            "turnover_rate": 0.5254592572635759
        },
        {
            "date": "2024-03-04",
            "pre_close": 3537.8,
            "open": 3538.37,
            "high": 3548.69,
            "low": 3519.76,
            "close": 3540.87,
            "change": 3.07,
            "change_percent": 0.08677709310871162,
            "trading_volume": 163244613,
            "trading_value": 297719931809.3,
            "turnover_rate": 0.5271871231947709
        },
        {
            "date": "2024-03-05",
            "pre_close": 3540.87,
            "open": 3524.96,
            "high": 3570.69,
            "low": 3519.08,
            "close": 3565.51,
            "change": 24.64,
            "change_percent": 0.6958741778150568,
            "trading_volume": 166422389,
            "trading_value": 299895929709.1,
            "turnover_rate": 0.5374356172122043
        },
        {
            "date": "2024-03-06",
            "pre_close": 3565.51,
            "open": 3556.53,
            "high": 3577.39,
            "low": 3545.1,
            "close": 3551.05,
            "change": -14.46,
            "change_percent": -0.40555208090848155,
            "trading_volume": 143076613,
            "trading_value": 248294165707.4,
            "turnover_rate": 0.462044014687727
        },
        {
            "date": "2024-03-07",
            "pre_close": 3551.05,
            "open": 3548.1,
            "high": 3569.92,
            "low": 3522.9,
            "close": 3529.72,
            "change": -21.33,
            "change_percent": -0.6006674082313682,
            "trading_volume": 148110510,
            "trading_value": 251839533036.1,
            "turnover_rate": 0.4783002789973117
        },
        {
            "date": "2024-03-08",
            "pre_close": 3529.72,
            "open": 3529.55,
            "high": 3548.51,
            "low": 3511.58,
            "close": 3544.91,
            "change": 15.19,
            "change_percent": 0.430345749804517,
            "trading_volume": 125792664,
            "trading_value": 225379101014.0,
            "turnover_rate": 0.4062233685469245
        },
        {
            "date": "2024-03-11",
            "pre_close": 3544.91,
            "open": 3545.94,
            "high": 3589.26,
            "low": 3542.28,
            "close": 3589.26,
            "change": 44.35,
            "change_percent": 1.2510895904268373,
            "trading_volume": 148202825,
            "trading_value": 286418582154.6,
            "turnover_rate": 0.4785904046544981
        },
        {
            "date": "2024-03-12",
            "pre_close": 3589.26,
            "open": 3592.58,
            "high": 3605.7,
            "low": 3574.21,
            "close": 3597.49,
            "change": 8.23,
            "change_percent": 0.22929517505001032,
            "trading_volume": 180685560,
            "trading_value": 339997042337.1,
            "turnover_rate": 0.5834864476198653
        },
        {
            "date": "2024-03-13",
            "pre_close": 3597.49,
            "open": 3594.42,
            "high": 3594.42,
            "low": 3563.37,
            "close": 3572.36,
            "change": -25.13,
            "change_percent": -0.6985425949759415,
            "trading_volume": 144590590,
            "trading_value": 266898756379.8,
            "turnover_rate": 0.4669228445945987
        },
        {
            "date": "2024-03-14",
            "pre_close": 3572.36,
            "open": 3571.79,
            "high": 3597.46,
            "low": 3545.61,
            "close": 3562.22,
            "change": -10.14,
            "change_percent": -0.2838459729702493,
            "trading_volume": 140962722,
            "trading_value": 263803609335.2,
            "turnover_rate": 0.4552074568528141
        },
        {
            "date": "2024-03-15",
            "pre_close": 3562.22,
            "open": 3554.91,
            "high": 3572.81,
            "low": 3533.68,
            "close": 3569.99,
            "change": 7.77,
            "change_percent": 0.21812240681372852,
            "trading_volume": 138316044,
            "trading_value": 243991558366.2,
            "turnover_rate": 0.4466605764251881
        },
        {
            "date": "2024-03-18",
            "pre_close": 3569.99,
            "open": 3577.06,
            "high": 3604.05,
            "low": 3573.4,
            "close": 3603.53,
            "change": 33.54,
            "change_percent": 0.9394984299675909,
            "trading_volume": 160379438,
            "trading_value": 295314840611.0,
            "turnover_rate": 0.5179093483785959
        },
        {
            "date": "2024-03-19",
            "pre_close": 3603.53,
            "open": 3593.34,
            "high": 3610.74,
            "low": 3577.19,
            "close": 3577.63,
            "change": -25.9,
            "change_percent": -0.7187396802579692,
            "trading_volume": 145571786,
            "trading_value": 259553448413.4,
            "turnover_rate": 0.47011627480688367
        },
        {
            "date": "2024-03-20",
            "pre_close": 3577.63,
            "open": 3568.72,
            "high": 3589.55,
            "low": 3568.43,
            "close": 3585.38,
            "change": 7.75,
            "change_percent": 0.21662385433932518,
            "trading_volume": 129528966,
            "trading_value": 223752103886.2,
            "turnover_rate": 0.41830914480963394
        },
        {
            "date": "2024-03-21",
            "pre_close": 3585.38,
            "open": 3593.07,
            "high": 3601.11,
            "low": 3575.03,
            "close": 3581.09,
            "change": -4.29,
            "change_percent": -0.11965258912583882,
            "trading_volume": 130743377,
            "trading_value": 233162492629.6,
            "turnover_rate": 0.42223103498111836
        },
        {
            "date": "2024-03-22",
            "pre_close": 3581.09,
            "open": 3571.27,
            "high": 3575.72,
            "low": 3522.84,
            "close": 3545.0,
            "change": -36.09,
            "change_percent": -1.0077937164382913,
            "trading_volume": 139227358,
            "trading_value": 248850931022.2,
            "turnover_rate": 0.4496229975279089
        },
        {
            "date": "2024-03-25",
            "pre_close": 3545.0,
            "open": 3536.71,
            "high": 3564.96,
            "low": 3525.76,
            "close": 3525.76,
            "change": -19.24,
            "change_percent": -0.5427362482369534,
            "trading_volume": 137015724,
            "trading_value": 233747256235.1,
            "turnover_rate": 0.4424476038552695
        },
        {
            "date": "2024-03-26",
            "pre_close": 3525.76,
            "open": 3526.68,
            "high": 3547.65,
            "low": 3518.6,
            "close": 3543.75,
            "change": 17.99,
            "change_percent": 0.5102445997458704,
            "trading_volume": 126209535,
            "trading_value": 226730734844.1,
            "turnover_rate": 0.40755208929592285
        },
        {
            "date": "2024-03-27",
            "pre_close": 3543.75,
            "open": 3538.72,
            "high": 3542.96,
            "low": 3502.79,
            "close": 3502.79,
            "change": -40.96,
            "change_percent": -1.155837742504409,
            "trading_volume": 128626763,
            "trading_value": 216404726565.9,
            "turnover_rate": 0.41535772235852836
        },
        {
            "date": "2024-03-28",
            "pre_close": 3502.79,
            "open": 3498.48,
            "high": 3551.21,
            "low": 3489.39,
            "close": 3520.96,
            "change": 18.17,
            "change_percent": 0.518729355742137,
            "trading_volume": 143334717,
            "trading_value": 232530806334.5,
            "turnover_rate": 0.4628519915215913
        },
        {
            "date": "2024-03-29",
            "pre_close": 3520.96,
            "open": 3516.88,
            "high": 3538.24,
            "low": 3516.88,
            "close": 3537.48,
            "change": 16.52,
            "change_percent": 0.4691902208488594,
            "trading_volume": 128643290,
            "trading_value": 201749384356.7,
            "turnover_rate": 0.41541001703483926
        },
        {
            "date": "2024-04-01",
            "pre_close": 3537.48,
            "open": 3551.58,
            "high": 3600.92,
            "low": 3551.58,
            "close": 3595.65,
            "change": 58.17,
            "change_percent": 1.6443909223515043,
            "trading_volume": 162776561,
            "trading_value": 251637272845.1,
            "turnover_rate": 0.5256311479014286
        },
        {
            "date": "2024-04-02",
            "pre_close": 3595.65,
            "open": 3593.22,
            "high": 3596.19,
            "low": 3568.75,
            "close": 3580.68,
            "change": -14.97,
            "change_percent": -0.41633640649117687,
            "trading_volume": 141272972,
            "trading_value": 220207515542.9,
            "turnover_rate": 0.45538420975150784
        },
        {
            "date": "2024-04-03",
            "pre_close": 3580.68,
            "open": 3578.68,
            "high": 3582.43,
            "low": 3558.87,
            "close": 3567.8,
            "change": -12.88,
            "change_percent": -0.35970821184802887,
            "trading_volume": 135592331,
            "trading_value": 214222897580.1,
            "turnover_rate": 0.4370728637422448
        },
        {
            "date": "2024-04-08",
            "pre_close": 3567.8,
            "open": 3553.56,
            "high": 3567.82,
            "low": 3535.77,
            "close": 3536.41,
            "change": -31.39,
            "change_percent": -0.8798138909131679,
            "trading_volume": 155304283,
            "trading_value": 243249251687.2,
            "turnover_rate": 0.50061290231011
        },
        {
            "date": "2024-04-09",
            "pre_close": 3536.41,
            "open": 3533.38,
            "high": 3543.71,
            "low": 3518.86,
            "close": 3533.49,
            "change": -2.92,
            "change_percent": -0.08256961155522126,
            "trading_volume": 129670942,
            "trading_value": 195893525574.7,
            "turnover_rate": 0.4179855530443159
        },
        {
            "date": "2024-04-10",
            "pre_close": 3533.49,
            "open": 3528.97,
            "high": 3531.23,
            "low": 3490.05,
            "close": 3504.71,
            "change": -28.78,
            "change_percent": -0.8144921876105493,
            "trading_volume": 128790274,
            "trading_value": 199754768626.1,
            "turnover_rate": 0.41514661003886233
        },
        {
            "date": "2024-04-11",
            "pre_close": 3504.71,
            "open": 3485.03,
            "high": 3520.59,
            "low": 3484.93,
            "close": 3504.24,
            "change": -0.47,
            "change_percent": -0.013410524693911905,
            "trading_volume": 126534395,
            "trading_value": 200293481885.7,
            "turnover_rate": 0.4078622870307875
        },
        {
            "date": "2024-04-12",
            "pre_close": 3504.24,
            "open": 3505.75,
            "high": 3516.7,
            "low": 3470.06,
            "close": 3475.84,
            "change": -28.4,
            "change_percent": -0.810446773052074,
            "trading_volume": 128921116,
            "trading_value": 208566204702.9,
            "turnover_rate": 0.41555631159213924
        },
        {
            "date": "2024-04-15",
            "pre_close": 3475.84,
            "open": 3473.5,
            "high": 3552.41,
            "low": 3473.5,
            "close": 3549.08,
            "change": 73.24,
            "change_percent": 2.107116553120972,
            "trading_volume": 183941250,
            "trading_value": 267472484531.0,
            "turnover_rate": 0.5929047986490636
        },
        {
            "date": "2024-04-16",
            "pre_close": 3549.08,
            "open": 3533.36,
            "high": 3545.5,
            "low": 3503.62,
            "close": 3511.11,
            "change": -37.97,
            "change_percent": -1.0698547229141073,
            "trading_volume": 176153065,
            "trading_value": 253315972272.3,
            "turnover_rate": 0.5677924760131001
        },
        {
            "date": "2024-04-17",
            "pre_close": 3511.11,
            "open": 3509.13,
            "high": 3565.94,
            "low": 3498.03,
            "close": 3565.4,
            "change": 54.29,
            "change_percent": 1.5462346665299578,
            "trading_volume": 168466398,
            "trading_value": 244987812753.2,
            "turnover_rate": 0.5430161163839435
        },
        {
            "date": "2024-04-18",
            "pre_close": 3565.4,
            "open": 3550.56,
            "high": 3602.79,
            "low": 3547.6,
            "close": 3569.8,
            "change": 4.4,
            "change_percent": 0.12340831323273686,
            "trading_volume": 178574105,
            "trading_value": 261329927268.4,
            "turnover_rate": 0.5755961608373606
        },
        {
            "date": "2024-04-19",
            "pre_close": 3569.8,
            "open": 3550.61,
            "high": 3560.95,
            "low": 3529.32,
            "close": 3541.66,
            "change": -28.14,
            "change_percent": -0.7882794554316768,
            "trading_volume": 147281505,
            "trading_value": 226229520121.3,
            "turnover_rate": 0.4747310302372706
        },
        {
            "date": "2024-04-22",
            "pre_close": 3541.66,
            "open": 3536.18,
            "high": 3558.16,
            "low": 3528.02,
            "close": 3530.9,
            "change": -10.76,
            "change_percent": -0.30381233658792767,
            "trading_volume": 150579042,
            "trading_value": 229511183118.0,
            "turnover_rate": 0.48522394722164425
        },
        {
            "date": "2024-04-23",
            "pre_close": 3530.9,
            "open": 3525.67,
            "high": 3533.76,
            "low": 3499.98,
            "close": 3506.22,
            "change": -24.68,
            "change_percent": -0.6989719335013735,
            "trading_volume": 143113504,
            "trading_value": 213257232210.7,
            "turnover_rate": 0.46116689767052527
        },
        {
            "date": "2024-04-24",
            "pre_close": 3506.22,
            "open": 3514.01,
            "high": 3524.54,
            "low": 3495.65,
            "close": 3521.62,
            "change": 15.4,
            "change_percent": 0.4392194443018407,
            "trading_volume": 121739851,
            "trading_value": 195299919746.2,
            "turnover_rate": 0.3921890961840028
        },
        {
            "date": "2024-04-25",
            "pre_close": 3521.62,
            "open": 3510.64,
            "high": 3543.97,
            "low": 3505.2,
            "close": 3530.28,
            "change": 8.66,
            "change_percent": 0.2459095529898172,
            "trading_volume": 115187722,
            "trading_value": 184524622000.7,
            "turnover_rate": 0.3710814753214915
        },
        {
            "date": "2024-04-26",
            "pre_close": 3530.28,
            "open": 3531.96,
            "high": 3588.4,
            "low": 3531.96,
            "close": 3584.27,
            "change": 53.99,
            "change_percent": 1.5293404489162332,
            "trading_volume": 197216133,
            "trading_value": 308045062250.7,
            "turnover_rate": 0.6351301239664305
        },
        {
            "date": "2024-04-29",
            "pre_close": 3584.27,
            "open": 3584.54,
            "high": 3645.82,
            "low": 3578.76,
            "close": 3623.91,
            "change": 39.64,
            "change_percent": 1.1059434696604888,
            "trading_volume": 222721381,
            "trading_value": 358709708837.6,
            "turnover_rate": 0.7172490307743562
        },
        {
            "date": "2024-04-30",
            "pre_close": 3623.91,
            "open": 3619.26,
            "high": 3630.71,
            "low": 3604.39,
            "close": 3604.39,
            "change": -19.52,
            "change_percent": -0.5386447235168644,
            "trading_volume": 191296899,
            "trading_value": 286674161757.8,
            "turnover_rate": 0.61604939080515
        },
        {
            "date": "2024-05-06",
            "pre_close": 3604.39,
            "open": 3654.05,
            "high": 3668.26,
            "low": 3645.74,
            "close": 3657.88,
            "change": 53.49,
            "change_percent": 1.4840236489392102,
            "trading_volume": 208018007,
            "trading_value": 333270472130.0,
            "turnover_rate": 0.6698976097390652
        },
        {
            "date": "2024-05-07",
            "pre_close": 3657.88,
            "open": 3657.0,
            "high": 3665.68,
            "low": 3648.38,
            "close": 3659.01,
            "change": 1.13,
            "change_percent": 0.030892210788762888,
            "trading_volume": 164834286,
            "trading_value": 247368347983.1,
            "turnover_rate": 0.5308224094210671
        },
        {
            "date": "2024-05-08",
            "pre_close": 3659.01,
            "open": 3650.75,
            "high": 3650.94,
            "low": 3628.7,
            "close": 3630.22,
            "change": -28.79,
            "change_percent": -0.7868248515308787,
            "trading_volume": 130035336,
            "trading_value": 199923460349.8,
            "turnover_rate": 0.4187357823830776
        },
        {
            "date": "2024-05-09",
            "pre_close": 3630.22,
            "open": 3630.41,
            "high": 3669.76,
            "low": 3630.41,
            "close": 3664.56,
            "change": 34.34,
            "change_percent": 0.9459481794491794,
            "trading_volume": 146559017,
            "trading_value": 232694927940.9,
            "turnover_rate": 0.471939858658444
        },
        {
            "date": "2024-05-10",
            "pre_close": 3664.56,
            "open": 3669.09,
            "high": 3674.61,
            "low": 3641.76,
            "close": 3666.28,
            "change": 1.72,
            "change_percent": 0.04693605780775864,
            "trading_volume": 150720536,
            "trading_value": 233730562074.5,
            "turnover_rate": 0.4853405121680041
        },
        {
            "date": "2024-05-13",
            "pre_close": 3666.28,
            "open": 3646.35,
            "high": 3673.62,
            "low": 3634.6,
            "close": 3664.69,
            "change": -1.59,
            "change_percent": -0.04336820973848151,
            "trading_volume": 157267455,
            "trading_value": 249688465072.9,
            "turnover_rate": 0.5064223510939756
        },
        {
            "date": "2024-05-14",
            "pre_close": 3664.69,
            "open": 3668.23,
            "high": 3675.78,
            "low": 3646.71,
            "close": 3657.05,
            "change": -7.64,
            "change_percent": -0.20847602389288045,
            "trading_volume": 133406490,
            "trading_value": 214643548213.8,
            "turnover_rate": 0.42958812733948004
        },
        {
            "date": "2024-05-15",
            "pre_close": 3657.05,
            "open": 3651.05,
            "high": 3656.53,
            "low": 3624.0,
            "close": 3626.06,
            "change": -30.99,
            "change_percent": -0.8474043286255315,
            "trading_volume": 123522764,
            "trading_value": 191480969435.1,
            "turnover_rate": 0.3977611046919548
        },
        {
            "date": "2024-05-16",
            "pre_close": 3626.06,
            "open": 3636.6,
            "high": 3657.48,
            "low": 3626.33,
            "close": 3640.36,
            "change": 14.3,
            "change_percent": 0.3943674401416413,
            "trading_volume": 154630503,
            "trading_value": 240288953464.0,
            "turnover_rate": 0.4979215279017728
        },
        {
            "date": "2024-05-17",
            "pre_close": 3640.36,
            "open": 3638.56,
            "high": 3677.97,
            "low": 3627.45,
            "close": 3677.97,
            "change": 37.61,
            "change_percent": 1.0331395796020173,
            "trading_volume": 164570417,
            "trading_value": 247729525192.2,
            "turnover_rate": 0.5299287133368854
        },
        {
            "date": "2024-05-20",
            "pre_close": 3677.97,
            "open": 3682.06,
            "high": 3703.03,
            "low": 3677.44,
            "close": 3690.96,
            "change": 12.99,
            "change_percent": 0.35318395745479164,
            "trading_volume": 184609423,
            "trading_value": 279971341520.4,
            "turnover_rate": 0.5944310971051088
        },
        {
            "date": "2024-05-21",
            "pre_close": 3690.96,
            "open": 3682.29,
            "high": 3684.61,
            "low": 3665.15,
            "close": 3676.16,
            "change": -14.8,
            "change_percent": -0.4009796909205193,
            "trading_volume": 130678283,
            "trading_value": 196575354877.9,
            "turnover_rate": 0.42077637270643287
        },
        {
            "date": "2024-05-22",
            "pre_close": 3676.16,
            "open": 3675.65,
            "high": 3691.88,
            "low": 3667.09,
            "close": 3684.45,
            "change": 8.29,
            "change_percent": 0.22550705083565462,
            "trading_volume": 151914605,
            "trading_value": 230839373504.9,
            "turnover_rate": 0.48915607616530404
        },
        {
            "date": "2024-05-23",
            "pre_close": 3684.45,
            "open": 3672.84,
            "high": 3674.37,
            "low": 3633.51,
            "close": 3641.79,
            "change": -42.66,
            "change_percent": -1.1578390261775842,
            "trading_volume": 142572990,
            "trading_value": 214205039030.7,
            "turnover_rate": 0.4590672242672647
        },
        {
            "date": "2024-05-24",
            "pre_close": 3641.79,
            "open": 3630.83,
            "high": 3650.87,
            "low": 3599.67,
            "close": 3601.48,
            "change": -40.31,
            "change_percent": -1.106873268365282,
            "trading_volume": 124791177,
            "trading_value": 195344742155.9,
            "turnover_rate": 0.40181449499462885
        },
        {
            "date": "2024-05-27",
            "pre_close": 3601.48,
            "open": 3606.65,
            "high": 3638.15,
            "low": 3603.71,
            "close": 3635.71,
            "change": 34.23,
            "change_percent": 0.9504425958217178,
            "trading_volume": 131272644,
            "trading_value": 206143742535.6,
            "turnover_rate": 0.4225518870396945
        },
        {
            "date": "2024-05-28",
            "pre_close": 3635.71,
            "open": 3633.25,
            "high": 3638.97,
            "low": 3605.92,
            "close": 3609.17,
            "change": -26.54,
            "change_percent": -0.7299812141232386,
            "trading_volume": 123532238,
            "trading_value": 184381267979.1,
            "turnover_rate": 0.39763639006052337
        },
        {
            "date": "2024-05-29",
            "pre_close": 3609.17,
            "open": 3609.07,
            "high": 3633.2,
            "low": 3602.82,
            "close": 3613.52,
            "change": 4.35,
            "change_percent": 0.12052632599739,
            "trading_volume": 115906321,
            "trading_value": 179072813277.6,
            "turnover_rate": 0.373037521663199
        },
        {
            "date": "2024-05-30",
            "pre_close": 3613.52,
            "open": 3607.05,
            "high": 3624.04,
            "low": 3586.75,
            "close": 3594.31,
            "change": -19.21,
            "change_percent": -0.5316146029356418,
            "trading_volume": 122602995,
            "trading_value": 193069647050.8,
            "turnover_rate": 0.3945902909295097
        },
        {
            "date": "2024-05-31",
            "pre_close": 3594.31,
            "open": 3599.82,
            "high": 3614.64,
            "low": 3579.92,
            "close": 3579.92,
            "change": -14.39,
            "change_percent": -0.40035500555043946,
            "trading_volume": 112462019,
            "trading_value": 180707602931.7,
            "turnover_rate": 0.36195217574638777
        },
        {
            "date": "2024-06-03",
            "pre_close": 3579.92,
            "open": 3577.38,
            "high": 3600.6,
            "low": 3567.87,
            "close": 3588.75,
            "change": 8.83,
            "change_percent": 0.24665355650405596,
            "trading_volume": 141054591,
            "trading_value": 222756928174.4,
            "turnover_rate": 0.45393939941284656
        },
        {
            "date": "2024-06-04",
            "pre_close": 3588.75,
            "open": 3583.81,
            "high": 3622.5,
            "low": 3580.28,
            "close": 3615.67,
            "change": 26.92,
            "change_percent": 0.7501219087425984,
            "trading_volume": 124545096,
            "trading_value": 195790966233.8,
            "turnover_rate": 0.4008085672317257
        },
        {
            "date": "2024-06-05",
            "pre_close": 3615.67,
            "open": 3610.36,
            "high": 3623.32,
            "low": 3594.11,
            "close": 3594.79,
            "change": -20.88,
            "change_percent": -0.5774863303343503,
            "trading_volume": 110906766,
            "trading_value": 182639598874.9,
            "turnover_rate": 0.35691792824513047
        },
        {
            "date": "2024-06-06",
            "pre_close": 3594.79,
            "open": 3602.16,
            "high": 3625.01,
            "low": 3584.17,
            "close": 3592.25,
            "change": -2.54,
            "change_percent": -0.07065781311286612,
            "trading_volume": 137893517,
            "trading_value": 226764072639.2,
            "turnover_rate": 0.4436639588286325
        },
        {
            "date": "2024-06-07",
            "pre_close": 3592.25,
            "open": 3594.63,
            "high": 3603.07,
            "low": 3552.09,
            "close": 3574.11,
            "change": -18.14,
            "change_percent": -0.5049759899784257,
            "trading_volume": 131103026,
            "trading_value": 213001530097.8,
            "turnover_rate": 0.4217730390831378
        },
        {
            "date": "2024-06-11",
            "pre_close": 3574.11,
            "open": 3555.82,
            "high": 3565.31,
            "low": 3525.89,
            "close": 3542.88,
            "change": -31.23,
            "change_percent": -0.8737839630005791,
            "trading_volume": 134522306,
            "trading_value": 219282337214.0,
            "turnover_rate": 0.4306947701885255
        },
        {
            "date": "2024-06-12",
            "pre_close": 3542.88,
            "open": 3539.09,
            "high": 3551.17,
            "low": 3531.57,
            "close": 3544.12,
            "change": 1.24,
            "change_percent": 0.03499977419500519,
            "trading_volume": 122813729,
            "trading_value": 200722600631.1,
            "turnover_rate": 0.3931638861395354
        },
        {
            "date": "2024-06-13",
            "pre_close": 3544.12,
            "open": 3548.22,
            "high": 3551.08,
            "low": 3520.18,
            "close": 3526.13,
            "change": -17.99,
            "change_percent": -0.5076013227543086,
            "trading_volume": 123245462,
            "trading_value": 214792338449.3,
            "turnover_rate": 0.39448916729457145
        },
        {
            "date": "2024-06-14",
            "pre_close": 3526.13,
            "open": 3514.8,
            "high": 3547.15,
            "low": 3503.52,
            "close": 3541.53,
            "change": 15.4,
            "change_percent": 0.4367394282116655,
            "trading_volume": 171516942,
            "trading_value": 283768816845.0,
            "turnover_rate": 0.5489467837960883
        },
        {
            "date": "2024-06-17",
            "pre_close": 3541.53,
            "open": 3521.44,
            "high": 3540.79,
            "low": 3520.74,
            "close": 3536.2,
            "change": -5.33,
            "change_percent": -0.15049992517358318,
            "trading_volume": 137433438,
            "trading_value": 232293851893.9,
            "turnover_rate": 0.43892730082574155
        },
        {
            "date": "2024-06-18",
            "pre_close": 3536.2,
            "open": 3533.49,
            "high": 3551.71,
            "low": 3532.78,
            "close": 3545.59,
            "change": 9.39,
            "change_percent": 0.26553927945251965,
            "trading_volume": 123671838,
            "trading_value": 208824124156.0,
            "turnover_rate": 0.3949760663952695
        },
        {
            "date": "2024-06-19",
            "pre_close": 3545.59,
            "open": 3543.36,
            "high": 3543.36,
            "low": 3524.84,
            "close": 3528.75,
            "change": -16.84,
            "change_percent": -0.47495621321134146,
            "trading_volume": 106642797,
            "trading_value": 184790298728.6,
            "turnover_rate": 0.34058969638654435
        },
        {
            "date": "2024-06-20",
            "pre_close": 3528.75,
            "open": 3525.17,
            "high": 3533.99,
            "low": 3500.13,
            "close": 3503.28,
            "change": -25.47,
            "change_percent": -0.7217853347502656,
            "trading_volume": 111617396,
            "trading_value": 186515776574.7,
            "turnover_rate": 0.3564347178980355
        },
        {
            "date": "2024-06-21",
            "pre_close": 3503.28,
            "open": 3496.34,
            "high": 3505.51,
            "low": 3473.83,
            "close": 3495.62,
            "change": -7.66,
            "change_percent": -0.21865223447740403,
            "trading_volume": 109186615,
            "trading_value": 182736735066.8,
            "turnover_rate": 0.348674872229687
        },
        {
            "date": "2024-06-24",
            "pre_close": 3495.62,
            "open": 3473.64,
            "high": 3505.78,
            "low": 3471.22,
            "close": 3476.81,
            "change": -18.81,
            "change_percent": -0.5381019676051745,
            "trading_volume": 117990184,
            "trading_value": 195787549313.6,
            "turnover_rate": 0.3766872118915381
        },
        {
            "date": "2024-06-25",
            "pre_close": 3476.81,
            "open": 3475.16,
            "high": 3483.22,
            "low": 3440.65,
            "close": 3457.9,
            "change": -18.91,
            "change_percent": -0.5438893698534001,
            "trading_volume": 118448118,
            "trading_value": 190886336762.4,
            "turnover_rate": 0.37814917996246117
        },
        {
            "date": "2024-06-26",
            "pre_close": 3457.9,
            "open": 3451.54,
            "high": 3487.4,
            "low": 3442.3,
            "close": 3480.26,
            "change": 22.36,
            "change_percent": 0.6466352410422511,
            "trading_volume": 105898861,
            "trading_value": 171538111702.3,
            "turnover_rate": 0.3380848571653012
        },
        {
            "date": "2024-06-27",
            "pre_close": 3480.26,
            "open": 3467.29,
            "high": 3471.14,
            "low": 3452.58,
            "close": 3454.12,
            "change": -26.14,
            "change_percent": -0.7510933091205829,
            "trading_volume": 114918101,
            "trading_value": 174112508796.1,
            "turnover_rate": 0.3668785647117809
        },
        {
            "date": "2024-06-28",
            "pre_close": 3454.12,
            "open": 3443.67,
            "high": 3484.68,
            "low": 3443.67,
            "close": 3461.66,
            "change": 7.54,
            "change_percent": 0.2182900420367561,
            "trading_volume": 135409153,
            "trading_value": 205118806811.8,
            "turnover_rate": 0.4323064553312955
        },
        {
            "date": "2024-07-01",
            "pre_close": 3461.66,
            "open": 3458.26,
            "high": 3479.95,
            "low": 3443.81,
            "close": 3478.18,
            "change": 16.52,
            "change_percent": 0.4772276884500499,
            "trading_volume": 121829770,
            "trading_value": 188018227774.8,
            "turnover_rate": 0.3889522150229586
        },
        {
            "date": "2024-07-02",
            "pre_close": 3478.18,
            "open": 3472.45,
            "high": 3488.32,
            "low": 3464.52,
            "close": 3471.79,
            "change": -6.39,
            "change_percent": -0.1837167714149354,
            "trading_volume": 121650121,
            "trading_value": 186104752421.9,
            "turnover_rate": 0.3883761806893034
        },
        {
            "date": "2024-07-03",
            "pre_close": 3471.79,
            "open": 3471.56,
            "high": 3478.7,
            "low": 3454.99,
            "close": 3463.41,
            "change": -8.38,
            "change_percent": -0.2413740462412761,
            "trading_volume": 103857108,
            "trading_value": 163035359363.1,
            "turnover_rate": 0.3315150144579309
        },
        {
            "date": "2024-07-04",
            "pre_close": 3463.41,
            "open": 3468.3,
            "high": 3483.31,
            "low": 3444.93,
            "close": 3445.81,
            "change": -17.6,
            "change_percent": -0.5081696940298722,
            "trading_volume": 104429909,
            "trading_value": 159477153569.5,
            "turnover_rate": 0.33334341176774107
        },
        {
            "date": "2024-07-05",
            "pre_close": 3445.81,
            "open": 3443.36,
            "high": 3451.04,
            "low": 3399.67,
            "close": 3431.06,
            "change": -14.75,
            "change_percent": -0.4280561029191975,
            "trading_volume": 116609659,
            "trading_value": 181416567402.8,
            "turnover_rate": 0.3722212563524918
        },
        {
            "date": "2024-07-08",
            "pre_close": 3431.06,
            "open": 3420.8,
            "high": 3428.04,
            "low": 3395.91,
            "close": 3401.76,
            "change": -29.3,
            "change_percent": -0.8539634981609182,
            "trading_volume": 115528218,
            "trading_value": 177559765827.5,
            "turnover_rate": 0.36860458631025983
        },
        {
            "date": "2024-07-09",
            "pre_close": 3401.76,
            "open": 3396.8,
            "high": 3448.93,
            "low": 3384.81,
            "close": 3439.81,
            "change": 38.05,
            "change_percent": 1.1185386388222567,
            "trading_volume": 131629443,
            "trading_value": 215048837819.8,
            "turnover_rate": 0.4199622012155383
        },
        {
            "date": "2024-07-10",
            "pre_close": 3439.81,
            "open": 3425.88,
            "high": 3447.51,
            "low": 3423.65,
            "close": 3428.97,
            "change": -10.84,
            "change_percent": -0.3151336847093299,
            "trading_volume": 127203456,
            "trading_value": 198149476849.1,
            "turnover_rate": 0.4058411413621485
        },
        {
            "date": "2024-07-11",
            "pre_close": 3428.97,
            "open": 3451.04,
            "high": 3473.98,
            "low": 3438.12,
            "close": 3468.17,
            "change": 39.2,
            "change_percent": 1.1432004362826156,
            "trading_volume": 145892466,
            "trading_value": 237551298481.6,
            "turnover_rate": 0.4654675199377229
        },
        {
            "date": "2024-07-12",
            "pre_close": 3468.17,
            "open": 3459.96,
            "high": 3479.1,
            "low": 3457.36,
            "close": 3472.4,
            "change": 4.23,
            "change_percent": 0.12196633959696325,
            "trading_volume": 130874589,
            "trading_value": 205055553856.4,
            "turnover_rate": 0.41740155396184164
        },
        {
            "date": "2024-07-15",
            "pre_close": 3472.4,
            "open": 3462.61,
            "high": 3481.46,
            "low": 3460.79,
            "close": 3476.25,
            "change": 3.85,
            "change_percent": 0.1108743232346504,
            "trading_volume": 118517083,
            "trading_value": 171584915379.5,
            "turnover_rate": 0.3779869578470578
        },
        {
            "date": "2024-07-16",
            "pre_close": 3476.25,
            "open": 3466.85,
            "high": 3500.29,
            "low": 3464.37,
            "close": 3498.28,
            "change": 22.03,
            "change_percent": 0.6337288745055735,
            "trading_volume": 120659017,
            "trading_value": 200456285077.5,
            "turnover_rate": 0.38481820793069216
        },
        {
            "date": "2024-07-17",
            "pre_close": 3498.28,
            "open": 3494.21,
            "high": 3514.48,
            "low": 3486.22,
            "close": 3501.58,
            "change": 3.3,
            "change_percent": 0.09433207176097967,
            "trading_volume": 131802062,
            "trading_value": 222830802528.4,
            "turnover_rate": 0.42027417355355123
        },
        {
            "date": "2024-07-18",
            "pre_close": 3501.58,
            "open": 3483.3,
            "high": 3522.8,
            "low": 3475.72,
            "close": 3520.93,
            "change": 19.35,
            "change_percent": 0.5526076799616173,
            "trading_volume": 123768199,
            "trading_value": 215783795702.6,
            "turnover_rate": 0.39465721289900396
        },
        {
            "date": "2024-07-19",
            "pre_close": 3520.93,
            "open": 3500.81,
            "high": 3545.34,
            "low": 3493.07,
            "close": 3539.02,
            "change": 18.09,
            "change_percent": 0.513784710289611,
            "trading_volume": 132447975,
            "trading_value": 228065104129.0,
            "turnover_rate": 0.42226709534241674
        },
        {
            "date": "2024-07-22",
            "pre_close": 3539.02,
            "open": 3538.4,
            "high": 3540.19,
            "low": 3494.01,
            "close": 3514.92,
            "change": -24.1,
            "change_percent": -0.6809794801950823,
            "trading_volume": 132126337,
            "trading_value": 217457320403.9,
            "turnover_rate": 0.42124075687983586
        },
        {
            "date": "2024-07-23",
            "pre_close": 3514.92,
            "open": 3509.79,
            "high": 3509.79,
            "low": 3439.88,
            "close": 3439.88,
            "change": -75.04,
            "change_percent": -2.134899229569948,
            "trading_volume": 128897660,
            "trading_value": 202857560168.7,
            "turnover_rate": 0.41094680134280803
        },
        {
            "date": "2024-07-24",
            "pre_close": 3439.88,
            "open": 3432.35,
            "high": 3451.42,
            "low": 3408.41,
            "close": 3418.17,
            "change": -21.71,
            "change_percent": -0.6311266672093213,
            "trading_volume": 127036263,
            "trading_value": 184884499786.8,
            "turnover_rate": 0.40501188117232845
        },
        {
            "date": "2024-07-25",
            "pre_close": 3418.17,
            "open": 3404.61,
            "high": 3415.86,
            "low": 3383.8,
            "close": 3399.27,
            "change": -18.9,
            "change_percent": -0.5529274436321189,
            "trading_volume": 131022242,
            "trading_value": 190131464834.7,
            "turnover_rate": 0.4177046944444918
        },
        {
            "date": "2024-07-26",
            "pre_close": 3399.27,
            "open": 3403.71,
            "high": 3420.82,
            "low": 3388.66,
            "close": 3409.29,
            "change": 10.02,
            "change_percent": 0.2947691710278972,
            "trading_volume": 124195558,
            "trading_value": 187853329477.8,
            "turnover_rate": 0.3959298099354738
        },
        {
            "date": "2024-07-29",
            "pre_close": 3409.29,
            "open": 3404.37,
            "high": 3408.5,
            "low": 3388.84,
            "close": 3390.74,
            "change": -18.55,
            "change_percent": -0.5441015578023577,
            "trading_volume": 109787786,
            "trading_value": 166697103823.1,
            "turnover_rate": 0.3499941776646018
        },
        {
            "date": "2024-07-30",
            "pre_close": 3390.74,
            "open": 3380.69,
            "high": 3380.69,
            "low": 3352.8,
            "close": 3369.38,
            "change": -21.36,
            "change_percent": -0.6299509841509523,
            "trading_volume": 104952164,
            "trading_value": 165442824490.2,
            "turnover_rate": 0.33457787535245354
        },
        {
            "date": "2024-07-31",
            "pre_close": 3369.38,
            "open": 3364.03,
            "high": 3445.0,
            "low": 3364.03,
            "close": 3442.08,
            "change": 72.7,
            "change_percent": 2.157666989179018,
            "trading_volume": 171959177,
            "trading_value": 258249147336.4,
            "turnover_rate": 0.5481900301340793
        },
        {
            "date": "2024-08-01",
            "pre_close": 3442.08,
            "open": 3443.14,
            "high": 3448.34,
            "low": 3419.19,
            "close": 3419.27,
            "change": -22.81,
            "change_percent": -0.6626807046901874,
            "trading_volume": 136323464,
            "trading_value": 206038002517.7,
            "turnover_rate": 0.4345869505786545
        },
        {
            "date": "2024-08-02",
            "pre_close": 3419.27,
            "open": 3393.92,
            "high": 3419.1,
            "low": 3380.96,
            "close": 3384.39,
            "change": -34.88,
            "change_percent": -1.0201007817458114,
            "trading_volume": 116615255,
            "trading_value": 179671192427.6,
            "turnover_rate": 0.37174928097411125
        },
        {
            "date": "2024-08-05",
            "pre_close": 3384.39,
            "open": 3362.11,
            "high": 3409.03,
            "low": 3343.32,
            "close": 3343.32,
            "change": -41.07,
            "change_percent": -1.2135126270908494,
            "trading_volume": 142812516,
            "trading_value": 223631266563.2,
            "turnover_rate": 0.4552622812938795
        },
        {
            "date": "2024-08-06",
            "pre_close": 3343.32,
            "open": 3367.35,
            "high": 3376.8,
            "low": 3318.63,
            "close": 3342.98,
            "change": -0.34,
            "change_percent": -0.01016953208188268,
            "trading_volume": 119340279,
            "trading_value": 181724693847.5,
            "turnover_rate": 0.3804367279690963
        },
        {
            "date": "2024-08-07",
            "pre_close": 3342.98,
            "open": 3338.59,
            "high": 3362.38,
            "low": 3329.97,
            "close": 3341.49,
            "change": -1.49,
            "change_percent": -0.04457101149274001,
            "trading_volume": 95084377,
            "trading_value": 145078975325.5,
            "turnover_rate": 0.30311367948342327
        },
        {
            "date": "2024-08-08",
            "pre_close": 3341.49,
            "open": 3332.43,
            "high": 3364.79,
            "low": 3320.84,
            "close": 3342.94,
            "change": 1.45,
            "change_percent": 0.043393815333878004,
            "trading_volume": 92495695,
            "trading_value": 149482926226.5,
            "turnover_rate": 0.2948281359794317
        },
        {
            "date": "2024-08-09",
            "pre_close": 3342.94,
            "open": 3358.13,
            "high": 3366.67,
            "low": 3331.63,
            "close": 3331.63,
            "change": -11.31,
            "change_percent": -0.33832494750130127,
            "trading_volume": 91511626,
            "trading_value": 142852166559.2,
            "turnover_rate": 0.29169152931272835
        },
        {
            "date": "2024-08-12",
            "pre_close": 3331.63,
            "open": 3327.56,
            "high": 3338.08,
            "low": 3319.89,
            "close": 3325.86,
            "change": -5.77,
            "change_percent": -0.1731884993231541,
            "trading_volume": 79938754,
            "trading_value": 117544892726.5,
            "turnover_rate": 0.25480284431026345
        },
        {
            "date": "2024-08-13",
            "pre_close": 3325.86,
            "open": 3328.01,
            "high": 3335.01,
            "low": 3310.19,
            "close": 3334.39,
            "change": 8.53,
            "change_percent": 0.2564750169880873,
            "trading_volume": 84489679,
            "trading_value": 125259155343.0,
            "turnover_rate": 0.26930880764117415
        },
        {
            "date": "2024-08-14",
            "pre_close": 3334.39,
            "open": 3332.79,
            "high": 3332.79,
            "low": 3309.1,
            "close": 3309.24,
            "change": -25.15,
            "change_percent": -0.7542608992949235,
            "trading_volume": 78742407,
            "trading_value": 118181952004.2,
            "turnover_rate": 0.2509895271376662
        },
        {
            "date": "2024-08-15",
            "pre_close": 3309.24,
            "open": 3301.45,
            "high": 3356.76,
            "low": 3297.97,
            "close": 3341.95,
            "change": 32.71,
            "change_percent": 0.9884444766774244,
            "trading_volume": 104766399,
            "trading_value": 149249335425.5,
            "turnover_rate": 0.3338572376421783
        },
        {
            "date": "2024-08-16",
            "pre_close": 3341.95,
            "open": 3342.03,
            "high": 3356.91,
            "low": 3335.62,
            "close": 3345.63,
            "change": 3.68,
            "change_percent": 0.11011535181555679,
            "trading_volume": 96519083,
            "trading_value": 135885323083.0,
            "turnover_rate": 0.30757565414824184
        },
        {
            "date": "2024-08-19",
            "pre_close": 3345.63,
            "open": 3344.26,
            "high": 3375.96,
            "low": 3343.71,
            "close": 3356.97,
            "change": 11.34,
            "change_percent": 0.3389496148707418,
            "trading_volume": 105571110,
            "trading_value": 143421671337.3,
            "turnover_rate": 0.33642182396070636
        },
        {
            "date": "2024-08-20",
            "pre_close": 3356.97,
            "open": 3361.64,
            "high": 3362.33,
            "low": 3321.64,
            "close": 3332.7,
            "change": -24.27,
            "change_percent": -0.7229733956514357,
            "trading_volume": 101668331,
            "trading_value": 137910585091.6,
            "turnover_rate": 0.32391737827272177
        },
        {
            "date": "2024-08-21",
            "pre_close": 3332.7,
            "open": 3322.91,
            "high": 3339.44,
            "low": 3307.99,
            "close": 3321.64,
            "change": -11.06,
            "change_percent": -0.33186305398025623,
            "trading_volume": 89954751,
            "trading_value": 130005992563.3,
            "turnover_rate": 0.28659771577773224
        },
        {
            "date": "2024-08-22",
            "pre_close": 3321.64,
            "open": 3322.87,
            "high": 3327.7,
            "low": 3305.25,
            "close": 3313.14,
            "change": -8.5,
            "change_percent": -0.25589768909333943,
            "trading_volume": 100366504,
            "trading_value": 147702791560.6,
            "turnover_rate": 0.31976966944148105
        },
        {
            "date": "2024-08-23",
            "pre_close": 3313.14,
            "open": 3305.93,
            "high": 3336.24,
            "low": 3305.64,
            "close": 3327.19,
            "change": 14.05,
            "change_percent": 0.4240690100629614,
            "trading_volume": 89525774,
            "trading_value": 132680886499.7,
            "turnover_rate": 0.28523277615321313
        },
        {
            "date": "2024-08-26",
            "pre_close": 3327.19,
            "open": 3330.72,
            "high": 3336.53,
            "low": 3311.57,
            "close": 3324.22,
            "change": -2.97,
            "change_percent": -0.08926451450022391,
            "trading_volume": 93990772,
            "trading_value": 139070603958.0,
            "turnover_rate": 0.2994583997868135
        },
        {
            "date": "2024-08-27",
            "pre_close": 3324.22,
            "open": 3315.69,
            "high": 3320.57,
            "low": 3299.56,
            "close": 3305.33,
            "change": -18.89,
            "change_percent": -0.5682536053570462,
            "trading_volume": 95808157,
            "trading_value": 129755962864.4,
            "turnover_rate": 0.3052495208755787
        },
        {
            "date": "2024-08-28",
            "pre_close": 3305.33,
            "open": 3298.91,
            "high": 3305.35,
            "low": 3274.59,
            "close": 3286.5,
            "change": -18.83,
            "change_percent": -0.5696859315106207,
            "trading_volume": 92696650,
            "trading_value": 135982310964.6,
            "turnover_rate": 0.29533616420824516
        },
        {
            "date": "2024-08-29",
            "pre_close": 3286.5,
            "open": 3273.54,
            "high": 3290.79,
            "low": 3269.53,
            "close": 3277.68,
            "change": -8.82,
            "change_percent": -0.268370607028754,
            "trading_volume": 130702333,
            "trading_value": 174340106392.6,
            "turnover_rate": 0.41642410928673884
        },
        {
            "date": "2024-08-30",
            "pre_close": 3277.68,
            "open": 3273.75,
            "high": 3351.63,
            "low": 3273.65,
            "close": 3321.43,
            "change": 43.75,
            "change_percent": 1.3347855800444217,
            "trading_volume": 188695443,
            "trading_value": 268376041210.9,
            "turnover_rate": 0.6011908465452475
        },
        {
            "date": "2024-09-02",
            "pre_close": 3321.43,
            "open": 3307.54,
            "high": 3307.76,
            "low": 3264.76,
            "close": 3265.01,
            "change": -56.42,
            "change_percent": -1.698665936057662,
            "trading_volume": 147612353,
            "trading_value": 194409996348.3,
            "turnover_rate": 0.4702945122061467
        },
        {
            "date": "2024-09-03",
            "pre_close": 3265.01,
            "open": 3261.74,
            "high": 3281.59,
            "low": 3261.19,
            "close": 3273.43,
            "change": 8.42,
            "change_percent": 0.2578858870263797,
            "trading_volume": 122897306,
            "trading_value": 155089488535.3,
            "turnover_rate": 0.391552004725919
        },
        {
            "date": "2024-09-04",
            "pre_close": 3273.43,
            "open": 3253.9,
            "high": 3272.99,
            "low": 3249.98,
            "close": 3252.16,
            "change": -21.27,
            "change_percent": -0.6497771450741271,
            "trading_volume": 104832482,
            "trading_value": 140070063076.9,
            "turnover_rate": 0.33399730082577794
        },
        {
            "date": "2024-09-05",
            "pre_close": 3252.16,
            "open": 3252.96,
            "high": 3266.88,
            "low": 3247.17,
            "close": 3257.76,
            "change": 5.6,
            "change_percent": 0.17219325002459904,
            "trading_volume": 97109450,
            "trading_value": 134618198893.7,
            "turnover_rate": 0.309403583135619
        },
        {
            "date": "2024-09-06",
            "pre_close": 3257.76,
            "open": 3261.15,
            "high": 3274.81,
            "low": 3231.07,
            "close": 3231.35,
            "change": -26.41,
            "change_percent": -0.8106797308580129,
            "trading_volume": 88400417,
            "trading_value": 121541545905.7,
            "turnover_rate": 0.2816548654620628
        },
        {
            "date": "2024-09-09",
            "pre_close": 3231.35,
            "open": 3214.8,
            "high": 3222.93,
            "low": 3180.93,
            "close": 3192.95,
            "change": -38.4,
            "change_percent": -1.188357807108484,
            "trading_volume": 108673069,
            "trading_value": 146516054460.5,
            "turnover_rate": 0.34624232352721174
        },
        {
            "date": "2024-09-10",
            "pre_close": 3192.95,
            "open": 3193.46,
            "high": 3205.1,
            "low": 3171.79,
            "close": 3195.76,
            "change": 2.81,
            "change_percent": 0.08800638907593292,
            "trading_volume": 97290078,
            "trading_value": 133610476131.5,
            "turnover_rate": 0.3099796368507521
        },
        {
            "date": "2024-09-11",
            "pre_close": 3195.76,
            "open": 3187.05,
            "high": 3197.34,
            "low": 3174.03,
            "close": 3186.13,
            "change": -9.63,
            "change_percent": -0.30133677122186897,
            "trading_volume": 102482110,
            "trading_value": 141513837135.3,
            "turnover_rate": 0.32642110559965926
        },
        {
            "date": "2024-09-12",
            "pre_close": 3186.13,
            "open": 3189.43,
            "high": 3201.55,
            "low": 3171.88,
            "close": 3172.47,
            "change": -13.66,
            "change_percent": -0.42873329085756073,
            "trading_volume": 92868657,
            "trading_value": 136387244637.1,
            "turnover_rate": 0.2957991563804755
        },
        {
            "date": "2024-09-13",
            "pre_close": 3172.47,
            "open": 3174.03,
            "high": 3188.91,
            "low": 3159.25,
            "close": 3159.25,
            "change": -13.22,
            "change_percent": -0.41671000829007054,
            "trading_volume": 88336677,
            "trading_value": 137448911397.4,
            "turnover_rate": 0.28136414484743116
        },
        {
            "date": "2024-09-18",
            "pre_close": 3159.25,
            "open": 3158.82,
            "high": 3179.9,
            "low": 3145.79,
            "close": 3171.01,
            "change": 11.76,
            "change_percent": 0.3722402468940413,
            "trading_volume": 84722814,
            "trading_value": 123452147968.9,
            "turnover_rate": 0.2698533591401864
        },
        {
            "date": "2024-09-19",
            "pre_close": 3171.01,
            "open": 3178.4,
            "high": 3213.84,
            "low": 3149.79,
            "close": 3196.04,
            "change": 25.03,
            "change_percent": 0.7893384126823946,
            "trading_volume": 125439272,
            "trading_value": 181785109712.7,
            "turnover_rate": 0.3995883935606365
        },
        {
            "date": "2024-09-20",
            "pre_close": 3196.04,
            "open": 3192.43,
            "high": 3207.99,
            "low": 3173.22,
            "close": 3201.05,
            "change": 5.01,
            "change_percent": 0.15675648615161264,
            "trading_volume": 118064098,
            "trading_value": 163985054956.9,
            "turnover_rate": 0.37609427682314206
        },
        {
            "date": "2024-09-23",
            "pre_close": 3201.05,
            "open": 3200.87,
            "high": 3230.16,
            "low": 3198.02,
            "close": 3212.76,
            "change": 11.71,
            "change_percent": 0.3658174661439215,
            "trading_volume": 95344855,
            "trading_value": 143876166860.9,
            "turnover_rate": 0.30372189089741697
        },
        {
            "date": "2024-09-24",
            "pre_close": 3212.76,
            "open": 3244.65,
            "high": 3351.97,
            "low": 3222.49,
            "close": 3351.91,
            "change": 139.15,
            "change_percent": 4.331166971700345,
            "trading_volume": 204072217,
            "trading_value": 307879526847.5,
            "turnover_rate": 0.6500730336392271
        },
        {
            "date": "2024-09-25",
            "pre_close": 3351.91,
            "open": 3403.7,
            "high": 3465.49,
            "low": 3393.44,
            "close": 3401.53,
            "change": 49.62,
            "change_percent": 1.480350009397627,
            "trading_volume": 241564255,
            "trading_value": 356862584939.5,
            "turnover_rate": 0.7695041019064824
        },
        {
            "date": "2024-09-26",
            "pre_close": 3401.53,
            "open": 3399.32,
            "high": 3545.32,
            "low": 3391.68,
            "close": 3545.32,
            "change": 143.79,
            "change_percent": 4.227215400128766,
            "trading_volume": 243134010,
            "trading_value": 373983643044.8,
            "turnover_rate": 0.7745045640464138
        },
        {
            "date": "2024-09-27",
            "pre_close": 3545.32,
            "open": 3617.92,
            "high": 3708.5,
            "low": 3596.58,
            "close": 3703.68,
            "change": 158.36,
            "change_percent": 4.4667336093779975,
            "trading_volume": 265487774,
            "trading_value": 466692757481.8,
            "turnover_rate": 0.845712220745122
        },
        {
            "date": "2024-09-30",
            "pre_close": 3703.68,
            "open": 3846.65,
            "high": 4038.7,
            "low": 3796.5,
            "close": 4017.85,
            "change": 314.17,
            "change_percent": 8.48264428892345,
            "trading_volume": 510217707,
            "trading_value": 862528807419.2,
            "turnover_rate": 1.61592852231248
        },
        {
            "date": "2024-10-08",
            "pre_close": 4017.85,
            "open": 4450.37,
            "high": 4450.37,
            "low": 4094.35,
            "close": 4256.1,
            "change": 238.25,
            "change_percent": 5.929788319623679,
            "trading_volume": 589867894,
            "trading_value": 1130387437130.1,
            "turnover_rate": 1.868172488936521
        },
        {
            "date": "2024-10-09",
            "pre_close": 4256.1,
            "open": 4168.84,
            "high": 4197.6,
            "low": 3942.51,
            "close": 3955.98,
            "change": -300.12,
            "change_percent": -7.051526044970748,
            "trading_volume": 482269295,
            "trading_value": 1029032062193.4,
            "turnover_rate": 1.5272038039226983
        },
        {
            "date": "2024-10-10",
            "pre_close": 3955.98,
            "open": 3979.61,
            "high": 4098.5,
            "low": 3912.77,
            "close": 3997.79,
            "change": 41.81,
            "change_percent": 1.0568809751313202,
            "trading_volume": 395053099,
            "trading_value": 717952217512.6,
            "turnover_rate": 1.2510153691356833
        },
        {
            "date": "2024-10-11",
            "pre_close": 3997.79,
            "open": 3969.76,
            "high": 3978.24,
            "low": 3847.12,
            "close": 3887.17,
            "change": -110.62,
            "change_percent": -2.76702878340283,
            "trading_volume": 274096505,
            "trading_value": 484998267295.6,
            "turnover_rate": 0.8679534850408229
        },
        {
            "date": "2024-10-14",
            "pre_close": 3887.17,
            "open": 3915.22,
            "high": 3979.54,
            "low": 3868.78,
            "close": 3961.34,
            "change": 74.17,
            "change_percent": 1.908071939225709,
            "trading_volume": 307578993,
            "trading_value": 534076602215.5,
            "turnover_rate": 0.9739790695240601
        },
        {
            "date": "2024-10-15",
            "pre_close": 3961.34,
            "open": 3942.53,
            "high": 3967.87,
            "low": 3855.99,
            "close": 3855.99,
            "change": -105.35,
            "change_percent": -2.6594536192298563,
            "trading_volume": 242486448,
            "trading_value": 434410916723.5,
            "turnover_rate": 0.7678564327403902
        },
        {
            "date": "2024-10-16",
            "pre_close": 3855.99,
            "open": 3806.14,
            "high": 3877.75,
            "low": 3805.09,
            "close": 3831.59,
            "change": -24.4,
            "change_percent": -0.6327817240189939,
            "trading_volume": 218866407,
            "trading_value": 377301324426.4,
            "turnover_rate": 0.6930634338825366
        },
        {
            "date": "2024-10-17",
            "pre_close": 3831.59,
            "open": 3853.84,
            "high": 3882.07,
            "low": 3787.75,
            "close": 3788.22,
            "change": -43.37,
            "change_percent": -1.1319060755456614,
            "trading_volume": 212313820,
            "trading_value": 369170521634.5,
            "turnover_rate": 0.6723136219304078
        },
        {
            "date": "2024-10-18",
            "pre_close": 3788.22,
            "open": 3780.31,
            "high": 3998.21,
            "low": 3765.16,
            "close": 3925.23,
            "change": 137.01,
            "change_percent": 3.616738204222564,
            "trading_volume": 312958834,
            "trading_value": 620673701894.1,
            "turnover_rate": 0.9910149326399701
        },
        {
            "date": "2024-10-21",
            "pre_close": 3925.23,
            "open": 3946.9,
            "high": 3979.26,
            "low": 3896.17,
            "close": 3935.2,
            "change": 9.97,
            "change_percent": 0.25399785490277005,
            "trading_volume": 291185634,
            "trading_value": 600109598949.1,
            "turnover_rate": 0.9220767126102345
        },
        {
            "date": "2024-10-22",
            "pre_close": 3935.2,
            "open": 3923.74,
            "high": 3965.91,
            "low": 3917.52,
            "close": 3957.78,
            "change": 22.58,
            "change_percent": 0.5737954868875789,
            "trading_volume": 223433396,
            "trading_value": 442881846813.7,
            "turnover_rate": 0.7075151398347739
        },
        {
            "date": "2024-10-23",
            "pre_close": 3957.78,
            "open": 3955.32,
            "high": 4012.18,
            "low": 3939.1,
            "close": 3973.21,
            "change": 15.43,
            "change_percent": 0.38986502534249,
            "trading_volume": 245873949,
            "trading_value": 469120806272.1,
            "turnover_rate": 0.7785742404449498
        },
        {
            "date": "2024-10-24",
            "pre_close": 3973.21,
            "open": 3950.9,
            "high": 3957.98,
            "low": 3914.09,
            "close": 3928.83,
            "change": -44.38,
            "change_percent": -1.1169809801143156,
            "trading_volume": 174724062,
            "trading_value": 340486884485.3,
            "turnover_rate": 0.5532502758782347
        },
        {
            "date": "2024-10-25",
            "pre_close": 3928.83,
            "open": 3931.32,
            "high": 3992.89,
            "low": 3921.94,
            "close": 3956.42,
            "change": 27.59,
            "change_percent": 0.7022446886223125,
            "trading_volume": 210694885,
            "trading_value": 412231378430.4,
            "turnover_rate": 0.6671414523238084
        },
        {
            "date": "2024-10-28",
            "pre_close": 3956.42,
            "open": 3953.11,
            "high": 3964.16,
            "low": 3917.2,
            "close": 3964.16,
            "change": 7.74,
            "change_percent": 0.19563140414819458,
            "trading_volume": 216160415,
            "trading_value": 390450182338.0,
            "turnover_rate": 0.6844188822976548
        },
        {
            "date": "2024-10-29",
            "pre_close": 3964.16,
            "open": 3970.01,
            "high": 3991.31,
            "low": 3921.58,
            "close": 3924.65,
            "change": -39.51,
            "change_percent": -0.9966802550855667,
            "trading_volume": 217293984,
            "trading_value": 429625020404.8,
            "turnover_rate": 0.6880121353265488
        }
    ]
}